vim_unitex/__init__.py
vim_unitex/unitex.py
vim_unitex-0.0.1.data/scripts/tex2unicode
vim_unitex-0.0.1.dist-info/LICENSE
vim_unitex-0.0.1.dist-info/METADATA
vim_unitex-0.0.1.dist-info/WHEEL
vim_unitex-0.0.1.dist-info/top_level.txt
vim_unitex-0.0.1.dist-info/RECORD
