Metadata-Version: 2.1
Name: vim-unitex
Version: 0.0.1
Summary: Replace Latex snippets with unicode
Home-page: http://bitbucket.com/ddrake999/vim_unitex
Author: Dow Drake
Author-email: dowdrake@msn.com
License: MIT
Platform: UNKNOWN
Classifier: Programming Language :: Python :: 3
Classifier: License :: OSI Approved :: MIT License
Classifier: Operating System :: OS Independent
Requires-Python: >=3.6
